json_inline/__init__.py
json_inline/recursive.py
json_inline/search.py
json_inline-0.1.8.dist-info/LICENSE
json_inline-0.1.8.dist-info/METADATA
json_inline-0.1.8.dist-info/WHEEL
json_inline-0.1.8.dist-info/top_level.txt
json_inline-0.1.8.dist-info/RECORD
