Metadata-Version: 2.1
Name: json-inline
Version: 0.1.8
Summary: JSON Low Code - Extract data inline
Home-page: https://github.com/bigpe/json-inline
Author: Aleskandr Sokolov
Author-email: bigpewm@gmail.com
License: MIT
Keywords: json,low code,lowcode,fetch,extract,inline
Platform: any
Classifier: Development Status :: 3 - Alpha
Classifier: Intended Audience :: Developers
Classifier: License :: OSI Approved :: MIT License
Classifier: Operating System :: OS Independent
Classifier: Programming Language :: Python
Classifier: Programming Language :: Python :: 3.5
Classifier: Programming Language :: Python :: 3.6
Classifier: Programming Language :: Python :: 3.7
Classifier: Programming Language :: Python :: 3.8
Classifier: Programming Language :: Python :: 3.9
Classifier: Topic :: Software Development :: Libraries :: Python Modules
Requires-Python: >=3.5.2
License-File: LICENSE
